django_postgres_views/__init__.py
django_postgres_views/apps.py
django_postgres_views/models.py
django_postgres_views/settings.py
django_postgres_views/signals.py
django_postgres_views/view.py
django_postgres_views/db/__init__.py
django_postgres_views/db/sql/__init__.py
django_postgres_views/db/sql/compiler.py
django_postgres_views/db/sql/query.py
django_postgres_views/management/__init__.py
django_postgres_views/management/commands/__init__.py
django_postgres_views/management/commands/clear_postgres_views.py
django_postgres_views/management/commands/sync_postgres_views.py
django_postgres_views-0.0.4.dist-info/METADATA
django_postgres_views-0.0.4.dist-info/WHEEL
django_postgres_views-0.0.4.dist-info/top_level.txt
django_postgres_views-0.0.4.dist-info/RECORD
