Metadata-Version: 2.1
Name: django-postgres-views
Version: 0.0.4
Summary: Support for PostgreSQL views in Django
Home-page: https://github.com/bashhack/django-postgres-views
Author: bashhack
Author-email: info@marclaughton.com
License: Public Domain
Platform: UNKNOWN
Classifier: Programming Language :: Python
Classifier: Programming Language :: Python :: 3.6
Classifier: Programming Language :: Python :: 3.7
Classifier: Programming Language :: Python :: 3.8
Classifier: Programming Language :: Python :: 3.9
Classifier: Framework :: Django
Classifier: Framework :: Django :: 2.2
Classifier: Framework :: Django :: 3.2
